cyanureGPU/__init__.py
cyanureGPU/constants.py
cyanureGPU/data_processing.py
cyanureGPU/estimators.py
cyanureGPU/logger.py
cyanureGPU/erm/__init__.py
cyanureGPU/erm/algebra.py
cyanureGPU/erm/erm.py
cyanureGPU/erm/multi_erm.py
cyanureGPU/erm/simple_erm.py
cyanureGPU/erm/param/__init__.py
cyanureGPU/erm/param/model_param.py
cyanureGPU/erm/param/problem_param.py
cyanureGPU/losses/__init__.py
cyanureGPU/losses/logistic.py
cyanureGPU/losses/loss.py
cyanureGPU/losses/loss_matrix.py
cyanureGPU/losses/multi_class_logistic.py
cyanureGPU/losses/square.py
cyanureGPU/losses/square_multiclass.py
cyanureGPU/losses/to_compile.py
cyanureGPU/regularizers/__init__.py
cyanureGPU/regularizers/lasso.py
cyanureGPU/regularizers/none.py
cyanureGPU/regularizers/regularizer.py
cyanureGPU/regularizers/regularizer_matrix.py
cyanureGPU/regularizers/ridge.py
cyanureGPU/solvers/__init__.py
cyanureGPU/solvers/accelerator.py
cyanureGPU/solvers/ista.py
cyanureGPU/solvers/solver.py
test/__init__.py
test/test_active_set.py
test/test_estimator.py
test/test_logistic_regression.py
cyanureGPU-1.0.2.dist-info/LICENSE
cyanureGPU-1.0.2.dist-info/METADATA
cyanureGPU-1.0.2.dist-info/WHEEL
cyanureGPU-1.0.2.dist-info/top_level.txt
cyanureGPU-1.0.2.dist-info/RECORD
