Metadata-Version: 2.1
Name: cyanureGPU
Version: 1.0.2
Summary: optimization toolbox for machine learning
Home-page: https://inria-thoth.github.io/cyanure_gpu/welcome.html
Author: Julien Mairal
Author-email: julien.mairal@inria.fr
License: bsd-3-clause
Platform: UNKNOWN
License-File: LICENSE
Requires-Dist: scikit-learn
Requires-Dist: torch (<2.3.0)
Requires-Dist: numpy (==1.26.4)
